MANIFEST.in
setup.py
src/twitter/__init__.py
src/twitter.common.recordio.egg-info/PKG-INFO
src/twitter.common.recordio.egg-info/SOURCES.txt
src/twitter.common.recordio.egg-info/dependency_links.txt
src/twitter.common.recordio.egg-info/namespace_packages.txt
src/twitter.common.recordio.egg-info/requires.txt
src/twitter.common.recordio.egg-info/top_level.txt
src/twitter.common.recordio.egg-info/zip-safe
src/twitter/common/__init__.py
src/twitter/common/recordio/__init__.py
src/twitter/common/recordio/filelike.py
src/twitter/common/recordio/recordio.py
src/twitter/common/recordio/thrift_recordio.py