Metadata-Version: 1.1
Name: twitter.common.recordio
Version: 0.3.3
Summary: twitter.common simple record reader/writer library
Home-page: https://github.com/twitter/commons
Author: UNKNOWN
Author-email: UNKNOWN
License: Apache License, Version 2.0
Platform: UNKNOWN
Classifier: Intended Audience :: Developers
Classifier: License :: OSI Approved :: Apache Software License
Classifier: Operating System :: OS Independent
Classifier: Programming Language :: Python
